linq/__init__.py
linq/linq.py
tests/__init__.py
tests/test_linq.py
linq_tool-0.1.14.dist-info/LICENSE
linq_tool-0.1.14.dist-info/METADATA
linq_tool-0.1.14.dist-info/WHEEL
linq_tool-0.1.14.dist-info/top_level.txt
linq_tool-0.1.14.dist-info/RECORD
