Metadata-Version: 2.1
Name: linq-tool
Version: 0.1.14
Summary: A LINQ-like library for Python inspired by C# LINQ using itertools and more-itertools internally.
Home-page: https://github.com/Zozi96/linq_tool
Author: Zozimo Fernandez
Author-email: zozi.fer96@gmail.com
Classifier: Programming Language :: Python :: 3
Classifier: License :: OSI Approved :: MIT License
Classifier: Operating System :: OS Independent
Requires-Python: >=3.8
License-File: LICENSE
Requires-Dist: more-itertools
